building_management/__init__.py
building_management/db_operations.py
building_management-0.1.1.dist-info/METADATA
building_management-0.1.1.dist-info/WHEEL
building_management-0.1.1.dist-info/top_level.txt
building_management-0.1.1.dist-info/RECORD
